coroflow/__init__.py
coroflow/requirements.txt
coroflow-4.0.1.dist-info/WHEEL
coroflow-4.0.1.dist-info/METADATA
coroflow-4.0.1.dist-info/RECORD
